aws_secrets_dict/__init__.py
aws_secrets_dict/aws_secrets_dict.py
aws_secrets_dict-1.2.0.dist-info/LICENSE.txt
aws_secrets_dict-1.2.0.dist-info/METADATA
aws_secrets_dict-1.2.0.dist-info/WHEEL
aws_secrets_dict-1.2.0.dist-info/top_level.txt
aws_secrets_dict-1.2.0.dist-info/RECORD
