Metadata-Version: 2.1
Name: aws_secrets_dict
Version: 1.2.0
Summary: A class allowing you to interact with the AWS Secrets Manager with python dictionary syntax.
Home-page: https://github.com/davocarli/aws_secrets_dictionary
Author: David Carli-Arnold
Author-email: davocarli@gmail.com
License: MIT
Keywords: AWS,AWS Secrets,aws-secrets,dictionary,class
Classifier: Development Status :: 5 - Production/Stable
Classifier: Intended Audience :: Developers
Classifier: Topic :: Software Development :: Build Tools
Classifier: License :: OSI Approved :: MIT License
Classifier: Programming Language :: Python :: 3
License-File: LICENSE.txt
Requires-Dist: boto3
